.gitignore
.project
.travis.yml
CHANGES.txt
README.rst
buildout.cfg
setup.py
.externalToolBuilders/nosetests-slowlog.launch
slowlog/__init__.py
slowlog/compat.py
slowlog/exc.py
slowlog/framestats.py
slowlog/logfile.py
slowlog/monitor.py
slowlog/tween.py
slowlog/wsgi.py
slowlog.egg-info/PKG-INFO
slowlog.egg-info/SOURCES.txt
slowlog.egg-info/dependency_links.txt
slowlog.egg-info/entry_points.txt
slowlog.egg-info/not-zip-safe
slowlog.egg-info/requires.txt
slowlog.egg-info/top_level.txt
slowlog/tests/__init__.py
slowlog/tests/test_exc.py
slowlog/tests/test_framestats.py
slowlog/tests/test_logfile.py
slowlog/tests/test_monitor.py
slowlog/tests/test_slowlog.py
slowlog/tests/test_tween.py
slowlog/tests/test_wsgi.py