Metadata-Version: 1.1
Name: slowlog
Version: 0.9
Summary: Log and graph slow Pyramid and WSGI apps
Home-page: https://github.com/hathawsh/slowlog
Author: Shane Hathaway
Author-email: shane@hathawaymix.org
License: BSD-derived (http://www.repoze.org/LICENSE.txt)
Platform: UNKNOWN
Classifier: Development Status :: 4 - Beta
Classifier: Intended Audience :: Developers
Classifier: Programming Language :: Python :: 2
Classifier: Programming Language :: Python :: 3
Classifier: License :: Repoze Public License
Classifier: Topic :: System :: Monitoring
